flexibletl/__init__.py
flexibletl-0.1.0.dist-info/WHEEL
flexibletl-0.1.0.dist-info/METADATA
flexibletl-0.1.0.dist-info/RECORD
