Metadata-Version: 2.1
Name: flexibletl
Version: 0.1.0
Summary: 
Author: John Doe
Author-email: john@example.com
Requires-Python: >=3.8,<3.11
Classifier: Programming Language :: Python :: 3
Classifier: Programming Language :: Python :: 3.10
Classifier: Programming Language :: Python :: 3.8
Classifier: Programming Language :: Python :: 3.9
Requires-Dist: Django (>=4.0.6,<5.0.0)
Requires-Dist: kedro (>=0.18.2,<0.19.0)
Requires-Dist: psycopg2-binary (>=2.9.3,<3.0.0)
